rally/__init__.py
rally/api.py
rally/consts.py
rally/exceptions.py
rally/py.typed
rally/aas/__init__.py
rally/cli/__init__.py
rally/cli/cliutils.py
rally/cli/envutils.py
rally/cli/main.py
rally/cli/task_results_loader.py
rally/cli/yamlutils.py
rally/cli/commands/__init__.py
rally/cli/commands/db.py
rally/cli/commands/deployment.py
rally/cli/commands/env.py
rally/cli/commands/plugin.py
rally/cli/commands/task.py
rally/cli/commands/verify.py
rally/common/__init__.py
rally/common/broker.py
rally/common/cfg.py
rally/common/fileutils.py
rally/common/logging.py
rally/common/opts.py
rally/common/sshutils.py
rally/common/streaming_algorithms.py
rally/common/utils.py
rally/common/validation.py
rally/common/version.py
rally/common/yamlutils.py
rally/common/db/__init__.py
rally/common/db/alembic.ini
rally/common/db/api.py
rally/common/db/models.py
rally/common/db/sa_types.py
rally/common/db/schema.py
rally/common/db/migrations/README.rst
rally/common/db/migrations/__init__.py
rally/common/db/migrations/env.py
rally/common/db/migrations/script.py.mako
rally/common/db/migrations/versions/2016_01_ca3626f62937_init_migration.py
rally/common/db/migrations/versions/2016_03_3177d36ea270_merge_credentials_from_users_and_admin.py
rally/common/db/migrations/versions/2016_04_4ef544102ba7_change_task_status_enum.py
rally/common/db/migrations/versions/2016_04_e654a0648db0_refactor_task_results.py
rally/common/db/migrations/versions/2016_07_54e844ebfbc3_update_deployment_configs.py
rally/common/db/migrations/versions/2016_08_32fada9b2fde_remove_admin_domain_name.py
rally/common/db/migrations/versions/2016_09_08e1515a576c_fix_invalid_verification_logs.py
rally/common/db/migrations/versions/2016_09_6ad4f426f005_add_hooks_to_task_result.py
rally/common/db/migrations/versions/2016_11_484cd9413e66_new_db_schema_for_verification_component.py
rally/common/db/migrations/versions/2016_12_37fdbb373e8d_fix_test_results_for_verifications.py
rally-5.0.1.dist-info/AUTHORS
rally-5.0.1.dist-info/LICENSE
rally-5.0.1.dist-info/METADATA
rally-5.0.1.dist-info/WHEEL
rally-5.0.1.dist-info/entry_points.txt
rally-5.0.1.dist-info/pbr.json
rally-5.0.1.dist-info/top_level.txt
rally-5.0.1.dist-info/RECORD
