Metadata-Version: 2.1
Name: rally
Version: 5.0.1
Summary: Generic Testing Framework & Tool that unifies all types of testing
Author-email: OpenStack <openstack-discuss@lists.openstack.org>
License: Apache License, Version 2.0
Project-URL: Homepage, https://rally.readthedocs.io/
Project-URL: Issues, https://bugs.launchpad.net/rally
Project-URL: Source, https://opendev.org/openstack/rally
Project-URL: Github, https://github.com/openstack/rally
Project-URL: Changelog, https://github.com/openstack/rally/blob/master/CHANGELOG.rst
Classifier: Environment :: OpenStack
Classifier: Intended Audience :: Developers
Classifier: Intended Audience :: Information Technology
Classifier: License :: OSI Approved :: Apache Software License
Classifier: Operating System :: POSIX :: Linux
Classifier: Programming Language :: Python
Classifier: Programming Language :: Python :: Implementation :: CPython
Classifier: Programming Language :: Python :: 3 :: Only
Classifier: Programming Language :: Python :: 3
Classifier: Programming Language :: Python :: 3.9
Classifier: Programming Language :: Python :: 3.10
Classifier: Programming Language :: Python :: 3.11
Classifier: Programming Language :: Python :: 3.12
Requires-Python: >=3.9
License-File: LICENSE
License-File: AUTHORS
Requires-Dist: alembic !=1.2.0,!=1.6.3
Requires-Dist: Jinja2
Requires-Dist: jsonschema
Requires-Dist: markupsafe
Requires-Dist: oslo.config !=4.3.0,!=4.4.0
Requires-Dist: oslo.db
Requires-Dist: oslo.log !=3.44.2,!=4.1.2,!=4.2.0,!=5.0.1,!=5.0.2,!=5.1.0
Requires-Dist: packaging !=20.5,!=20.6,!=20.7
Requires-Dist: paramiko !=2.9.0,!=2.9.1
Requires-Dist: pbr
Requires-Dist: PrettyTable !=3.4.0
Requires-Dist: pyOpenSSL
Requires-Dist: PyYAML
Requires-Dist: python-subunit
Requires-Dist: requests !=2.20.0,!=2.24.0
Requires-Dist: SQLAlchemy >=2
Requires-Dist: virtualenv !=16.3.0
Provides-Extra: mysql
Requires-Dist: PyMySQL >=0.7.6 ; extra == 'mysql'
Provides-Extra: postgres
Requires-Dist: psycopg2 >=2.5 ; extra == 'postgres'
